mars/__init__.py
mars/constants.py
mars/res_field_algorithm.py
mars/res_freq_algorithm.py
mars/save_procedures.py
mars/secular_approximation.py
mars/spectra_processing.py
mars/spectral_integration.py
mars/spin_system.py
mars/utils.py
mars/mesher/__init__.py
mars/mesher/axial_neigbour.py
mars/mesher/delanay_mesh.py
mars/mesher/delanay_neigbour.py
mars/mesher/experimental.py
mars/mesher/general_mesh.py
mars/optimization/__init__.py
mars/optimization/fitter.py
mars/optimization/interactions.py
mars/optimization/objectives.py
mars/particles/__init__.py
mars/particles/nuclei_db_creation.py
mars/particles/typed_particles.py
mars/population/__init__.py
mars/population/contexts.py
mars/population/matrix_generators.py
mars/population/rk4.py
mars/population/tr_utils.py
mars/population/transform.py
mars/population/parametric_dependance/profiles.py
mars/population/parametric_dependance/rates.py
mars/population/populators/core.py
mars/population/populators/density_population.py
mars/population/populators/level_population.py
mars/population/populators/stationary.py
mars/reader/__init__.py
mars/reader/bruker_reader.py
mars/spectra_manager/__init__.py
mars/spectra_manager/spectra_manager.py
mars/spectra_manager/wave_intensity_calculator.py
mars/visualization/__init__.py
mars/visualization/levels_plot.py
mars/visualization/spin_system_plot.py
mars/visualization/transitions_plot.py
mars_epr-0.0.2.dist-info/METADATA
mars_epr-0.0.2.dist-info/WHEEL
mars_epr-0.0.2.dist-info/top_level.txt
mars_epr-0.0.2.dist-info/RECORD
